metacluster/__init__.py
metacluster/metacluster.py
metacluster/mha_cluster.py
metacluster/data/Arrhythmia.csv
metacluster/data/Blood.csv
metacluster/data/BreastCancer.csv
metacluster/data/BreastEW.csv
metacluster/data/CongressEW.csv
metacluster/data/Digits.csv
metacluster/data/Glass.csv
metacluster/data/HeartEW.csv
metacluster/data/Hill-valley.csv
metacluster/data/Horse.csv
metacluster/data/Ionosphere.csv
metacluster/data/Iris.csv
metacluster/data/Lymphography.csv
metacluster/data/Madelon.csv
metacluster/data/Monk1.csv
metacluster/data/Monk2.csv
metacluster/data/Monk3.csv
metacluster/data/Sonar.csv
metacluster/data/Soybean-small.csv
metacluster/data/SpectEW.csv
metacluster/data/Tic-tac-toe.csv
metacluster/data/Vowel.csv
metacluster/data/WaveformEW.csv
metacluster/data/Wine.csv
metacluster/data/Zoo.csv
metacluster/data/aggregation.csv
metacluster/data/aniso.csv
metacluster/data/appendicitis.csv
metacluster/data/balance.csv
metacluster/data/banknote.csv
metacluster/data/blobs.csv
metacluster/data/circles.csv
metacluster/data/diagnosis_II.csv
metacluster/data/ecoli.csv
metacluster/data/flame.csv
metacluster/data/heart.csv
metacluster/data/jain.csv
metacluster/data/liver.csv
metacluster/data/moons.csv
metacluster/data/mouse.csv
metacluster/data/pathbased.csv
metacluster/data/seeds.csv
metacluster/data/segmentation.csv
metacluster/data/smiley.csv
metacluster/data/varied.csv
metacluster/data/vary-density.csv
metacluster/data/vertebral2.csv
metacluster/data/wdbc.csv
metacluster/utils/__init__.py
metacluster/utils/cluster.py
metacluster/utils/data_loader.py
metacluster/utils/encoder.py
metacluster/utils/io_util.py
metacluster/utils/mealpy_util.py
metacluster/utils/validator.py
metacluster/utils/visualize_util.py
metacluster-1.3.0.dist-info/licenses/LICENSE
metacluster-1.3.0.dist-info/METADATA
metacluster-1.3.0.dist-info/WHEEL
metacluster-1.3.0.dist-info/top_level.txt
metacluster-1.3.0.dist-info/RECORD
